it2/__init__.py
it2/cli.py
it2/commands/__init__.py
it2/commands/app.py
it2/commands/config_commands.py
it2/commands/monitor.py
it2/commands/profile.py
it2/commands/session.py
it2/commands/shortcuts.py
it2/commands/tab.py
it2/commands/window.py
it2/core/__init__.py
it2/core/connection.py
it2/core/errors.py
it2/core/session_handler.py
it2/utils/__init__.py
it2/utils/config.py
it2-0.1.8.dist-info/METADATA
it2-0.1.8.dist-info/WHEEL
it2-0.1.8.dist-info/entry_points.txt
it2-0.1.8.dist-info/licenses/LICENSE
it2-0.1.8.dist-info/RECORD
