Metadata-Version: 2.3
Name: it2
Version: 0.1.8
Summary: A powerful command-line interface for controlling iTerm2
Project-URL: Homepage, https://github.com/mkusaka/it2
Project-URL: Bug Tracker, https://github.com/mkusaka/it2/issues
Project-URL: Documentation, https://github.com/mkusaka/it2#readme
Project-URL: Source Code, https://github.com/mkusaka/it2
Project-URL: PyPI, https://pypi.org/project/it2/
Author-email: Your Name <your.email@example.com>
License: MIT License
License-File: LICENSE
Keywords: automation,cli,iterm2,macos,terminal
Classifier: Development Status :: 3 - Alpha
Classifier: Intended Audience :: Developers
Classifier: License :: OSI Approved :: MIT License
Classifier: Operating System :: MacOS :: MacOS X
Classifier: Programming Language :: Python :: 3
Classifier: Programming Language :: Python :: 3.8
Classifier: Programming Language :: Python :: 3.9
Classifier: Programming Language :: Python :: 3.10
Classifier: Programming Language :: Python :: 3.11
Classifier: Programming Language :: Python :: 3.12
Classifier: Programming Language :: Python :: 3.13
Requires-Python: >=3.8
Requires-Dist: click>=8.0
Requires-Dist: iterm2>=2.7
Requires-Dist: pyyaml>=6.0
Requires-Dist: rich>=10.0
Provides-Extra: dev
Requires-Dist: black>=22.0; extra == 'dev'
Requires-Dist: build>=1.0.0; extra == 'dev'
Requires-Dist: mypy>=1.0; extra == 'dev'
Requires-Dist: pytest-asyncio>=0.20; extra == 'dev'
Requires-Dist: pytest-cov>=4.0; extra == 'dev'
Requires-Dist: pytest-timeout>=2.1; extra == 'dev'
Requires-Dist: pytest>=7.0; extra == 'dev'
Requires-Dist: ruff>=0.0.240; extra == 'dev'
Requires-Dist: twine==6.0.1; extra == 'dev'
Requires-Dist: types-pyyaml>=6.0; extra == 'dev'
